Workbook

Sheet Assumptions
A1: INNOVATION AI — 3-YEAR FINANCIAL MODEL
A2: Key Assumptions
A3: Parameter | B3: Year 1 | C3: Year 2 | D3: Year 3
A4: AI CHATBOT (B2B SaaS)
A5: New customers / month | B5: 3 | C5: 6 | D5: 12
A6: Monthly churn rate | B6: 0.06 | C6: 0.04 | D6: 0.03
A7: ARPU ($/month) | B7: 299 | C7: 320 | D7: 340
A8: Gross margin % | B8: 0.65 | C8: 0.7 | D8: 0.75
A9: S&M spend ($/month) | B9: 5500 | C9: 9000 | D9: 15000
A10: Product & Eng ($/month) | B10: 3000 | C10: 5000 | D10: 8000
A11: DATA SERVICES
A12: New customers / month | B12: 1 | C12: 2 | D12: 4
A13: Monthly churn rate | B13: 0.04 | C13: 0.03 | D13: 0.02
A14: ACV / month ($/client) | B14: 1500 | C14: 1575 | D14: 1654
A15: Gross margin % | B15: 0.45 | C15: 0.5 | D15: 0.55
A16: S&M spend ($/month) | B16: 6000 | C16: 9000 | D16: 14000
A17: Delivery & Eng ($/month) | B17: 8000 | C17: 12000 | D17: 18000
A19: Unit Economics (AI Chatbot — Year 1)
A20: CAC ($) | B20: $1,833 | C20: $1,833
A21: LTV @ 3% churn ($) | B21: $6,478 | C21: 3.5x
A22: LTV/CAC | B22: 3.5x | C22: Healthy >3x
A23: CAC Payback (months) | B23: 9.4 mo | C23: < 12 mo benchmark ✓
A24: Breakeven customers | B24: 44 | C24: Month 8

Sheet AI Chatbot
A1: AI CHATBOT — 3-YEAR P&L
A2: Metric | B2: Year 1 | C2: Year 2 | D2: Year 3
A3: Period-end customers | B3: 26 | C3: 74 | D3: 174
B4: 26 | C4: 74 | D4: 174
A5: Revenue (annual) | B5: =B4*Assumptions!B6*12 -> 18.72 | C5: =C4*Assumptions!C6*12 -> 35.52 | D5: =D4*Assumptions!D6*12 -> 62.64
A6: Gross profit | B6: =B4*Assumptions!B6*12 -> 18.72 | C6: =C4*Assumptions!C6*12 -> 35.52 | D6: =D4*Assumptions!D6*12 -> 62.64
B7: =B6*Assumptions!B7 -> 5597.28 | C7: =C6*Assumptions!C7 -> 11366.4 | D7: =D6*Assumptions!D7 -> 21297.6
A8: S&M (annual) | B8: =Assumptions!B8*12 -> 7.8 | C8: =Assumptions!C8*12 -> 8.4 | D8: =Assumptions!D8*12 -> 9
A9: Product & Eng (annual) | B9: =Assumptions!B8*12 -> 7.8 | C9: =Assumptions!C8*12 -> 8.4 | D9: =Assumptions!D8*12 -> 9
A10: Total OpEx | B10: =Assumptions!B9*12 -> 66000 | C10: =Assumptions!C9*12 -> 108000 | D10: =Assumptions!D9*12 -> 180000
B11: =B9+B10 -> 66007.8 | C11: =C9+C10 -> 108008.4 | D11: =D9+D10 -> 180009
A12: Contribution Margin ($) | B12: =B7-B11 -> -60410.52 | C12: =C7-C11 -> -96642 | D12: =D7-D11 -> -158711.4
A13: Contribution Margin % | B13: =B7-B11 -> -60410.52 | C13: =C7-C11 -> -96642 | D13: =D7-D11 -> -158711.4
B14: =IF(B6=0,0,B13/B6) -> -3227.0577 | C14: =IF(C6=0,0,C13/C6) -> -2720.777 | D14: =IF(D6=0,0,D13/D6) -> -2533.7069
A15: * Period-end customers based on monthly churn simulation (see Assumptions tab)

Sheet Data Services
A1: DATA SERVICES — 3-YEAR P&L
A2: Metric | B2: Year 1 | C2: Year 2 | D2: Year 3
A3: Period-end customers | B3: 9.68 | C3: 27.13 | D3: 64.34
B4: 9.68 | C4: 27.13 | D4: 64.34
A5: Revenue (annual) | B5: =B4*Assumptions!B14*12 -> 174240 | C5: =C4*Assumptions!C14*12 -> 512757 | D5: =D4*Assumptions!D14*12 -> 1277020.3
A6: Gross profit | B6: =B4*Assumptions!B14*12 -> 174240 | C6: =C4*Assumptions!C14*12 -> 512757 | D6: =D4*Assumptions!D14*12 -> 1277020.3
B7: =B6*Assumptions!B15 -> 78408 | C7: =C6*Assumptions!C15 -> 256378.5 | D7: =D6*Assumptions!D15 -> 702361.18
A8: S&M (annual) | B8: =Assumptions!B16*12 -> 72000 | C8: =Assumptions!C16*12 -> 108000 | D8: =Assumptions!D16*12 -> 168000
A9: Delivery & Eng (annual) | B9: =Assumptions!B16*12 -> 72000 | C9: =Assumptions!C16*12 -> 108000 | D9: =Assumptions!D16*12 -> 168000
A10: Total OpEx | B10: =Assumptions!B17*12 -> 96000 | C10: =Assumptions!C17*12 -> 144000 | D10: =Assumptions!D17*12 -> 216000
B11: =B9+B10 -> 168000 | C11: =C9+C10 -> 252000 | D11: =D9+D10 -> 384000
A12: Contribution Margin ($) | B12: =B7-B11 -> -89592 | C12: =C7-C11 -> 4378.5 | D12: =D7-D11 -> 318361.18
A13: Contribution Margin % | B13: =B7-B11 -> -89592 | C13: =C7-C11 -> 4378.5 | D13: =D7-D11 -> 318361.18
B14: =IF(B6=0,0,B13/B6) -> -0.51418733 | C14: =IF(C6=0,0,C13/C6) -> 0.0085391326 | D14: =IF(D6=0,0,D13/D6) -> 0.24930001

Sheet Consolidated P&L
A1: INNOVATION AI — CONSOLIDATED 3-YEAR P&L
B2: Y1 Chatbot | C2: Y1 Data Svc | D2: Y1 Total | E2: Y2 Total | F2: Y3 Total | G2: 3Y Growth
A3: Revenue | B3: 93288 | C3: 174281 | D3: 267569 | E3: 796888 | F3: 1987036 | G3: =IF(D4=0,0,(F4-D4)/ABS(D4)) -> 7.79894
A4: Gross Profit | B4: 60637 | C4: 78426 | D4: 139063 | E4: 475276 | F4: 1223607
A5: Total OpEx | B5: 102000 | C5: 168000 | D5: 270000 | E5: 420000 | F5: 660000
A6: Contribution Margin | B6: -41363 | C6: -89574 | D6: -130937 | E6: 35276 | F6: 574854 | G6: Positive Y2
A7: CM % | B7: ='AI Chatbot'!B14 -> -3227.0577 | C7: ='Data Services'!B14 -> -0.51418733 | D7: =IF(D4=0,0,D6/D4) -> -0.94156605 | E7: =IF(E4=0,0,E6/E4) -> 0.074222136 | F7: =IF(F4=0,0,F6/F4) -> 0.4698028 | G7: N/A
A10: Key Takeaways
A11: AI Chatbot: Fast ramp, CM positive Year 2 (+$31K). Cash flow engine for early stage.
A12: Data Services: Slower start, CM turns positive Year 2 (+$4K), accelerates to +$318K by Year 3.
A13: Consolidated: Revenue scales 7.4x from Y1 ($268K) to Y3 ($1.99M). CM breakeven Year 2.
A14: Key risk: Churn assumption decline (6%→3% Chatbot, 4%→2% Data Svc) must be monitored monthly.

Sheet Unit Economics
A1: UNIT ECONOMICS — AI CHATBOT (Year 1 Base Case)
A2: Metric | B2: Value | C2: Formula / Note
A3: Monthly S&M + Eng spend | B3: 5500 | C3: $5,500/mo (1 SDR + tools + ads)
A4: New customers / month | B4: 3 | C4: Outbound sales assumption
A5: CAC | B5: 3 | C5: S&M spend ÷ new customers
B6: =B4/B5 -> 1
A7: ARPU / month | B7: 299 | C7: Growth tier ($299/mo)
A8: Gross margin | B8: 0.65 | C8: 65% after server + API costs
A9: Monthly churn (base) | B9: 299 | C9: 3% base case
A10: Customer lifetime (mo) | B10: 0.65 | C10: 1 ÷ churn rate
A11: LTV | B11: 0.03 | C11: ARPU × GM × Lifetime
A12: LTV / CAC | B12: =1/B11 -> 33.333333 | C12: Target >3x
A13: CAC Payback (months) | B13: =B9*B10*B12 -> 6478.3333 | C13: CAC ÷ (ARPU × GM)
B14: =B13/B6 -> 6478.3333
A15: Monthly churn (stress) | B15: =B6/(B9*B10) -> 0.0051453563 | C15: 6% stress case
A16: Customer lifetime (stress) | B16: =1/B18 -> 16.666667
A17: LTV (stress) | B17: =B9*B10*B19 -> 3239.1667
A18: LTV/CAC (stress) | B18: 0.06 | C18: Danger zone <2x
B19: =1/B18 -> 16.666667
B20: =B9*B10*B19 -> 3239.1667
B21: =B20/B6 -> 3239.1667
